cocoa/cli/__init__.py
cocoa/cli/cli.py
cocoa/cli/cli_protocol.py
cocoa/cli/command.py
cocoa/cli/group.py
cocoa/cli/inspect_wrapped.py
cocoa/cli/arg_types/__init__.py
cocoa/cli/arg_types/base/__init__.py
cocoa/cli/arg_types/base/keyword_arg.py
cocoa/cli/arg_types/base/positional_arg.py
cocoa/cli/arg_types/data_types/__init__.py
cocoa/cli/arg_types/data_types/assert_path.py
cocoa/cli/arg_types/data_types/assert_set.py
cocoa/cli/arg_types/data_types/check_if_multiarg.py
cocoa/cli/arg_types/data_types/context.py
cocoa/cli/arg_types/data_types/env.py
cocoa/cli/arg_types/data_types/import_instance.py
cocoa/cli/arg_types/data_types/import_type.py
cocoa/cli/arg_types/data_types/json_data.py
cocoa/cli/arg_types/data_types/json_file.py
cocoa/cli/arg_types/data_types/paths.py
cocoa/cli/arg_types/data_types/pattern.py
cocoa/cli/arg_types/data_types/raw_file.py
cocoa/cli/arg_types/data_types/reduce_pattern_type.py
cocoa/cli/arg_types/operators/__init__.py
cocoa/cli/arg_types/operators/chain.py
cocoa/cli/arg_types/operators/map.py
cocoa/cli/arg_types/operators/operator.py
cocoa/cli/help_message/__init__.py
cocoa/cli/help_message/cli_style.py
cocoa/cli/help_message/create_help_string.py
cocoa/cli/help_message/description_help_message.py
cocoa/cli/help_message/help_message.py
cocoa/cli/help_message/line_parsing.py
cocoa/cli/help_message/options_help_message.py
cocoa/cli/help_message/title_help_message.py
cocoa/ui/__init__.py
cocoa/ui/components/__init__.py
cocoa/ui/components/animated_status_bar/__init__.py
cocoa/ui/components/animated_status_bar/animated_status_bar.py
cocoa/ui/components/animated_status_bar/animated_status_bar_config.py
cocoa/ui/components/counter/__init__.py
cocoa/ui/components/counter/counter.py
cocoa/ui/components/counter/counter_config.py
cocoa/ui/components/empty/__init__.py
cocoa/ui/components/empty/empty.py
cocoa/ui/components/header/__init__.py
cocoa/ui/components/header/header.py
cocoa/ui/components/header/header_config.py
hyperlight_cocoa-0.4.1.dist-info/licenses/LICENSE
hyperlight_cocoa-0.4.1.dist-info/METADATA
hyperlight_cocoa-0.4.1.dist-info/WHEEL
hyperlight_cocoa-0.4.1.dist-info/top_level.txt
hyperlight_cocoa-0.4.1.dist-info/RECORD
