Metadata-Version: 2.4
Name: hyperlight-cocoa
Version: 0.4.1
Summary: Create beautiful, performant terminal UI and CLI apps.
Author-email: Ada Lundhe <adalundhe@lundhe.audio>
License: MIT License
Project-URL: Homepage, https://github.com/hyper-light/cocoa
Keywords: ui,terminal,ascii,graphics
Classifier: Programming Language :: Python :: 3.11
Classifier: Programming Language :: Python :: 3.12
Classifier: Programming Language :: Python :: 3.13
Classifier: License :: OSI Approved :: MIT License
Classifier: Operating System :: OS Independent
Requires-Python: >=3.11
License-File: LICENSE
Requires-Dist: pydantic
Dynamic: license-file
